py_any2text_parser/__init__.py
py_any2text_parser/pdf2text.py
py_any2text_parser/include/pdfcoordhelper.py
py_any2text_parser/include/pdfpagehelper.py
py_any2text_parser/include/pdftablehelper.py
py_any2text_parser/include/pdfunstructuredhelper.py
py_any2text_parser-1.0.2.dist-info/METADATA
py_any2text_parser-1.0.2.dist-info/WHEEL
py_any2text_parser-1.0.2.dist-info/top_level.txt
py_any2text_parser-1.0.2.dist-info/RECORD
