Metadata-Version: 2.1
Name: py_any2text_parser
Version: 1.0.2
Summary: Any2Text - any format to text using Unstructured.io
Author-email: Vanson Leung <vanson@vanportdev.com>
Classifier: Development Status :: 5 - Production/Stable
Classifier: License :: OSI Approved :: MIT License
Classifier: Programming Language :: Python :: 3
Classifier: Programming Language :: Python :: 3.10
Classifier: Programming Language :: Python :: 3.9
Requires-Python: >=3.9
